acgaws/__init__.py
acgaws/iamhelper.py
acgaws/regionhelper.py
acgaws-0.2.dist-info/METADATA
acgaws-0.2.dist-info/WHEEL
acgaws-0.2.dist-info/top_level.txt
acgaws-0.2.dist-info/RECORD
