Metadata-Version: 2.1
Name: acgaws
Version: 0.2
Summary: Library for reusable aws code
Home-page: http://github.com/AustinCloudGuru/acg-libraries
Author: Mark Honomichl
Author-email: mark@austincloud.guru
License: MIT
Platform: UNKNOWN
Classifier: Programming Language :: Python :: 3
Classifier: License :: OSI Approved :: MIT License
Classifier: Operating System :: OS Independent
Requires-Dist: boto3
Requires-Dist: awsretry
